numeric_sets/__init__.py
numeric_sets/main.py
numeric_sets_dyaroshevych-0.0.3.dist-info/LICENCE
numeric_sets_dyaroshevych-0.0.3.dist-info/METADATA
numeric_sets_dyaroshevych-0.0.3.dist-info/WHEEL
numeric_sets_dyaroshevych-0.0.3.dist-info/top_level.txt
numeric_sets_dyaroshevych-0.0.3.dist-info/RECORD
