Metadata-Version: 2.1
Name: numeric-sets-dyaroshevych
Version: 0.0.3
Summary: A package for performing operations on numeric sets
Home-page: https://github.com/dyaroshevych/numeric_sets
Author: Dmytro Yaroshevych
Author-email: dyaroshevych@gmail.com
License: UNKNOWN
Platform: UNKNOWN
Classifier: Programming Language :: Python :: 3
Classifier: License :: OSI Approved :: MIT License
Classifier: Operating System :: OS Independent
Requires-Python: >=3.8
